cli.py
lilliepy_build-1.0.dist-info/METADATA
lilliepy_build-1.0.dist-info/WHEEL
lilliepy_build-1.0.dist-info/entry_points.txt
lilliepy_build-1.0.dist-info/top_level.txt
lilliepy_build-1.0.dist-info/RECORD
